Workbook

Sheet Dashboard
A1: Data Architect Practical Tracker v6 (23 weeks, SnowPro Core added)
A2: Legend: cells marked EDIT (yellow with blue text) are yours to edit. Everything else is calculated. If you see no colours, your viewer is ignoring formatting: open the file in Excel or Google Sheets.
A4: Start date (Monday) | B4: 46314 | C4: << EDIT. Example value: change to your real start date (shown as a number if your viewer ignores formats)
A5: Practice-exam readiness target | B5: 0.8 | C5: << EDIT. Assumption: a self-set target (0.8 = 80%), not an official passing score. Check each vendor's passing score.
A6: Overall progress
A7: Weeks done | B7: =COUNTIF('Weekly Plan'!N2:N24,"Done") -> 0
A8: Total weeks | B8: =COUNTA('Weekly Plan'!A2:A24) -> 23
A9: % of weeks complete | B9: =IF(B8=0,0,B7/B8) -> 0
A10: Planned study hours | B10: ='Weekly Plan'!L25 -> 94
A11: Planned project hours | B11: ='Weekly Plan'!M25 -> 136
A12: Practical share of planned hours | B12: =IF(B10+B11=0,0,B11/(B10+B11)) -> 0.59130435
A13: Actual hours logged | B13: ='Weekly Plan'!O25 -> 0
A14: Planned end date | B14: =B4+B8*7-1 -> 46474
A15: Deliverables done | B15: =COUNTIF(Deliverables!G2:G31,"Done")&" / "&COUNTA(Deliverables!A2:A31) -> 0 / 30
A16: Udemy courses finished | B16: =COUNTIF('Udemy Courses'!J2:J13,"Done")&" / "&COUNTA('Udemy Courses'!A2:A13) -> 0 / 12
A17: Certifications passed | B17: =COUNTIF(Certifications!E2:E5,"Passed")&" / "&COUNTA(Certifications!A2:A5) -> 0 / 4
A18: Applications sent | B18: =COUNTIF('Application Log'!E2:E31,"Applied")+COUNTIF('Application Log'!E2:E31,"Interview")+COUNTIF('Application Log'!E2:E31,"Offer")+COUNTIF('Application Log'!E2:E31,"Rejected") -> 0
A19: Setup tasks done | B19: =COUNTIF(Setup!D2:D11,"Done")&" / "&COUNTA(Setup!B2:B11) -> 0 / 10
A20: Progress by phase
A21: Phase | B21: Weeks done | C21: Total weeks | D21: % complete
A22: 1 Data Modeling | B22: =COUNTIFS('Weekly Plan'!C2:C24,A22,'Weekly Plan'!N2:N24,"Done") -> 0 | C22: =COUNTIF('Weekly Plan'!C2:C24,A22) -> 3 | D22: =IF(C22=0,0,B22/C22) -> 0
A23: 2 SnowPro Core | B23: =COUNTIFS('Weekly Plan'!C2:C24,A23,'Weekly Plan'!N2:N24,"Done") -> 0 | C23: =COUNTIF('Weekly Plan'!C2:C24,A23) -> 3 | D23: =IF(C23=0,0,B23/C23) -> 0
A24: 3 SnowPro Architect | B24: =COUNTIFS('Weekly Plan'!C2:C24,A24,'Weekly Plan'!N2:N24,"Done") -> 0 | C24: =COUNTIF('Weekly Plan'!C2:C24,A24) -> 6 | D24: =IF(C24=0,0,B24/C24) -> 0
A25: 4 GCP Data Engineer | B25: =COUNTIFS('Weekly Plan'!C2:C24,A25,'Weekly Plan'!N2:N24,"Done") -> 0 | C25: =COUNTIF('Weekly Plan'!C2:C24,A25) -> 5 | D25: =IF(C25=0,0,B25/C25) -> 0
A26: 5 Governance & CDMP | B26: =COUNTIFS('Weekly Plan'!C2:C24,A26,'Weekly Plan'!N2:N24,"Done") -> 0 | C26: =COUNTIF('Weekly Plan'!C2:C24,A26) -> 4 | D26: =IF(C26=0,0,B26/C26) -> 0
A27: 6 Portfolio & Job Search | B27: =COUNTIFS('Weekly Plan'!C2:C24,A27,'Weekly Plan'!N2:N24,"Done") -> 0 | C27: =COUNTIF('Weekly Plan'!C2:C24,A27) -> 2 | D27: =IF(C27=0,0,B27/C27) -> 0
A28: Exam readiness (from Practice Exams sheet)
A29: Exam | B29: Attempts | C29: Best score | D29: Readiness
A30: SnowPro Core | B30: =COUNTIF('Practice Exams'!$A$3:$A$41,A30) -> 0 | C30: =SUMPRODUCT(MAX(('Practice Exams'!$A$3:$A$41=A30)*('Practice Exams'!$D$3:$D$41))) -> 0 | D30: =IF(B30=0,"No attempts yet",IF(C30>=$B$5,"Ready to book","Keep practicing")) -> No attempts yet
A31: SnowPro Advanced: Architect | B31: =COUNTIF('Practice Exams'!$A$3:$A$41,A31) -> 0 | C31: =SUMPRODUCT(MAX(('Practice Exams'!$A$3:$A$41=A31)*('Practice Exams'!$D$3:$D$41))) -> 0 | D31: =IF(B31=0,"No attempts yet",IF(C31>=$B$5,"Ready to book","Keep practicing")) -> No attempts yet
A32: Google Professional Data Engineer | B32: =COUNTIF('Practice Exams'!$A$3:$A$41,A32) -> 0 | C32: =SUMPRODUCT(MAX(('Practice Exams'!$A$3:$A$41=A32)*('Practice Exams'!$D$3:$D$41))) -> 0 | D32: =IF(B32=0,"No attempts yet",IF(C32>=$B$5,"Ready to book","Keep practicing")) -> No attempts yet
A33: CDMP Data Management Fundamentals | B33: =COUNTIF('Practice Exams'!$A$3:$A$41,A33) -> 0 | C33: =SUMPRODUCT(MAX(('Practice Exams'!$A$3:$A$41=A33)*('Practice Exams'!$D$3:$D$41))) -> 0 | D33: =IF(B33=0,"No attempts yet",IF(C33>=$B$5,"Ready to book","Keep practicing")) -> No attempts yet
A34: Udemy is support, not the backbone: keep the project hours. Study hours include Udemy video time. Raise them if an exam feels shaky.
A35: Check every link, exam code and price on the vendor page before relying on it.

Sheet This Week
A1: This week only: ignore everything else
A3: Week by today's date | B3: =MAX(1,MIN(23,INT((TODAY()-Dashboard!B4)/7)+1)) -> 1
A4: Override week (optional, type 1 to 23) | C4: << EDIT (optional). Leave empty to follow the calendar. Before your start date it shows week 1.
A5: Week shown | B5: =IF(B4="",B3,B4) -> 1
A7: Phase | B7: =INDEX('Weekly Plan'!$C$2:$C$24,MATCH($B$5,'Weekly Plan'!$A$2:$A$24,0))&"" -> 1 Data Modeling
A8: Week starts | B8: =INDEX('Weekly Plan'!$B$2:$B$24,MATCH($B$5,'Weekly Plan'!$A$2:$A$24,0)) -> 46314
A9: Learn: topic | B9: =INDEX('Weekly Plan'!$D$2:$D$24,MATCH($B$5,'Weekly Plan'!$A$2:$A$24,0))&"" -> Dimensional modeling: grain, facts, dimensions, conformed dimensions, bus matrix
A10: Learn: main resource | B10: =INDEX('Weekly Plan'!$E$2:$E$24,MATCH($B$5,'Weekly Plan'!$A$2:$A$24,0))&"" -> Coginiti: Dimensional Modeling and the Star Schema (guide)
A11: Udemy support | B11: =INDEX('Weekly Plan'!$G$2:$G$24,MATCH($B$5,'Weekly Plan'!$A$2:$A$24,0))&"" -> OPTIONAL: search 'dimensional modeling Kimball'; watch only the facts, dimensions, grain and bus-matrix sections
A12: Build: milestone | B12: =INDEX('Weekly Plan'!$H$2:$H$24,MATCH($B$5,'Weekly Plan'!$A$2:$A$24,0))&"" -> Create the GitHub repo (folders: docs/, adr/, ingestion/, dbt/, infra/, mcp/). Write the business scenario, requirements and source inventory. Draw the bus matrix for order-to-cash.
A13: Action this week | B13: =INDEX('Weekly Plan'!$I$2:$I$24,MATCH($B$5,'Weekly Plan'!$A$2:$A$24,0))&""
A14: Done when | B14: =INDEX('Weekly Plan'!$J$2:$J$24,MATCH($B$5,'Weekly Plan'!$A$2:$A$24,0))&"" -> README and bus matrix are committed
A15: Deliverables (IDs) | B15: =INDEX('Weekly Plan'!$K$2:$K$24,MATCH($B$5,'Weekly Plan'!$A$2:$A$24,0))&"" -> D01, D02
A16: Status (update on Weekly Plan) | B16: =INDEX('Weekly Plan'!$N$2:$N$24,MATCH($B$5,'Weekly Plan'!$A$2:$A$24,0))&"" -> Not started
A17: Link | B17: =HYPERLINK(INDEX('Weekly Plan'!$F$2:$F$24,MATCH($B$5,'Weekly Plan'!$A$2:$A$24,0)),"Open the main link") -> Open the main link
A18: Resource 2 | B18: =IF(INDEX('Weekly Plan'!$Q$2:$Q$24,MATCH($B$5,'Weekly Plan'!$A$2:$A$24,0))="","",IF(INDEX('Weekly Plan'!$R$2:$R$24,MATCH($B$5,'Weekly Plan'!$A$2:$A$24,0))="",INDEX('Weekly Plan'!$Q$2:$Q$24,MATCH($B$5,'Weekly Plan'!$A$2:$A$24,0)),HYPERLINK(INDEX('Weekly Plan'!$R$2:$R$24,MATCH($B$5,'Weekly Plan'!$A$2:$A$24,0)),INDEX('Weekly Plan'!$Q$2:$Q$24,MATCH($B$5,'Weekly Plan'!$A$2:$A$24,0))))) -> Microsoft Learn: Understand star schema
A19: Resource 3 / book | B19: =IF(INDEX('Weekly Plan'!$S$2:$S$24,MATCH($B$5,'Weekly Plan'!$A$2:$A$24,0))="","",IF(INDEX('Weekly Plan'!$T$2:$T$24,MATCH($B$5,'Weekly Plan'!$A$2:$A$24,0))="",INDEX('Weekly Plan'!$S$2:$S$24,MATCH($B$5,'Weekly Plan'!$A$2:$A$24,0)),HYPERLINK(INDEX('Weekly Plan'!$T$2:$T$24,MATCH($B$5,'Weekly Plan'!$A$2:$A$24,0)),INDEX('Weekly Plan'!$S$2:$S$24,MATCH($B$5,'Weekly Plan'!$A$2:$A$24,0))))) -> Book: The Data Warehouse Toolkit (Kimball and Ross), ch. 1-3 (borrow)
A21: Your 10-hour rhythm
A22: Day | B22: Task | C22: Hours
A23: Monday | B23: ="Learn: "&B10 -> Learn: Coginiti: Dimensional Modeling and the Star Schema (guide) | C23: 1.5
A24: Tuesday | B24: ="Learn: "&IF(B18="",B10,B18) -> Learn: Microsoft Learn: Understand star schema | C24: 1.5
A25: Wednesday | B25: Build: start the milestone above | C25: 2
A26: Thursday | B26: Build: continue the milestone above | C26: 1.5
A27: Saturday | B27: Build (main block): finish the milestone and commit the deliverable | C27: 3
A28: Sunday | B28: Update the tracker, plan next week | C28: 0.5
A29: Total rhythm hours | C29: =SUM(C23:C28) -> 10
A30: Planned this week (study + project) | C30: =INDEX('Weekly Plan'!$L$2:$L$24,MATCH($B$5,'Weekly Plan'!$A$2:$A$24,0))+INDEX('Weekly Plan'!$M$2:$M$24,MATCH($B$5,'Weekly Plan'!$A$2:$A$24,0)) -> 10
A32: If you fall behind
A33: 1. Shrink the week, not the plan: do the Build part and skip optional learning.
A34: 2. Protect three things: exam dates, ADRs, the finished README.
A35: 3. Cut first: optional Udemy courses, the streaming slice, Iceberg, the Airflow DAG.
A36: 4. Change the plan only on Sunday, never mid-week.

Sheet Setup
A1: # | B1: Do before week 1 | C1: Link | D1: Status [EDIT] | E1: Notes (you fill) [EDIT]
A2: 1 | B2: Read the SnowPro Core (COF-C03) official page and note the exam code, price, passing score and rules. Core is required before the Architect exam and is now weeks 4 to 6 of the plan | C2: https://learn.snowflake.com/en/certifications/snowpro-core-c03 | D2: Not started
A3: 2 | B3: Compare your hands-on Snowflake experience with Snowflake's recommendation of 2+ years in an architect-level role; if you are short, plan extra practice and project time | D3: Not started
A4: 3 | B4: Create a GitHub repo called orderflow | C4: https://github.com | D4: Not started
A5: 4 | B5: Set your real start date on the Dashboard | D5: Not started
A6: 5 | B6: Install Python 3 and a code editor | C6: https://www.python.org/downloads/ | D6: Not started
A7: 6 | B7: Install Docker (check licensing rules at your company) | C7: https://docs.docker.com/get-docker/ | D7: Not started
A8: 7 | B8: Open a Snowflake trial when week 4 is close (trial credits are time-limited) | C8: https://signup.snowflake.com | D8: Not started
A9: 8 | B9: Open a GCP free-tier account when week 10 is close and set a budget alert | C9: https://cloud.google.com/free | D9: Not started
A10: 9 | B10: Check you can log in to Udemy through your company | D10: Not started
A11: 10 | B11: Ask your manager if the company pays for exam vouchers or a training budget | D11: Not started

Sheet Weekly Plan
A1: Week | B1: Week starts | C1: Phase | D1: Study focus (learn) | E1: Resource 1 (main) | F1: Link 1 | G1: Udemy support | H1: Project milestone (build) | I1: Action this week | J1: Done when | K1: Deliverables | L1: Study hrs [EDIT] | M1: Project hrs [EDIT] | N1: Status [EDIT] | O1: Actual hrs [EDIT] | P1: Notes [EDIT] | Q1: Resource 2 | R1: Link 2 | S1: Resource 3 / book | T1: Link 3
A2: 1 | B2: =Dashboard!$B$4+(A2-1)*7 -> 46314 | C2: 1 Data Modeling | D2: Dimensional modeling: grain, facts, dimensions, conformed dimensions, bus matrix | E2: Coginiti: Dimensional Modeling and the Star Schema (guide) | F2: https://coginiti.co/learning/data-modeling/dimensional-modeling-star-schema/ | G2: OPTIONAL: search 'dimensional modeling Kimball'; watch only the facts, dimensions, grain and bus-matrix sections | H2: Create the GitHub repo (folders: docs/, adr/, ingestion/, dbt/, infra/, mcp/). Write the business scenario, requirements and source inventory. Draw the bus matrix for order-to-cash. | J2: README and bus matrix are committed | K2: D01, D02 | L2: 4 | M2: 6 | N2: Not started | Q2: Microsoft Learn: Understand star schema | R2: https://learn.microsoft.com/power-bi/guidance/star-schema | S2: Book: The Data Warehouse Toolkit (Kimball and Ross), ch. 1-3 (borrow)
A3: 2 | B3: =Dashboard!$B$4+(A3-1)*7 -> 46321 | C3: 1 Data Modeling | D3: Slowly changing dimensions, bridge tables, dbt snapshots | E3: dbt Fundamentals (dbt Labs, free, about 5 h) | F3: https://learn.getdbt.com | G3: OPTIONAL: only if dbt snapshots or SCD feel rusty | H3: Write a Python generator for synthetic EDI/API data (customers, products, orders/850, shipments/856, invoices/810, payments) with injected changes and bad records. Start the dbt project with an SCD2 customer snapshot. | J3: Script runs; snapshot shows history rows | K3: D03, D04 | L3: 4 | M3: 6 | N3: Not started | Q3: dbt docs: Snapshots (SCD2) | R3: https://docs.getdbt.com/docs/build/snapshots | S3: Kimball techniques page (checklist for SCD types) | T3: https://www.kimballgroup.com/data-warehouse-business-intelligence-resources/kimball-techniques/dimensional-modeling-techniques/
A4: 3 | B4: =Dashboard!$B$4+(A4-1)*7 -> 46328 | C4: 1 Data Modeling | D4: Data Vault 2.0, medallion layering, Kimball vs Data Vault vs OBT | E4: Data Vault 2.0: hubs, links, satellites (DEV Community) | F4: https://dev.to/gowthampotureddi/data-vault-2-0-for-data-engineering-hubs-links-satellites-hash-keys-automation-4bah | G4: OPTIONAL: search 'Data Vault 2.0' | H4: Draw the full order-to-cash logical model. Sketch the Data Vault alternative for core entities. Write ADR-001 explaining your choice per layer. | I4: BOOK the SnowPro Core exam (COF-C03) for the Friday of week 6. Check the current code, price and rules on Snowflake's page first | J4: Diagram and ADR-001 are committed | K4: D05, D06 | L4: 4 | M4: 6 | N4: Not started | Q4: AutomateDV worked example: Data Vault on Snowflake TPC-H | R4: https://automate-dv.readthedocs.io/en/latest/worked_example/ | S4: ADR templates | T4: https://adr.github.io
A5: 4 | B5: =Dashboard!$B$4+(A5-1)*7 -> 46335 | C5: 2 SnowPro Core | D5: Core domains: Snowflake architecture and key concepts, accounts and virtual warehouses, data loading and unloading | E5: Snowflake SnowPro Core (COF-C03) official exam page: read the domains first | F5: https://learn.snowflake.com/en/certifications/snowpro-core-c03 | G5: CORE: one SnowPro Core prep course that covers COF-C03. Many older courses cover the retired COF-C02, so check the course says COF-C03 and its update date | H5: Set up the Snowflake trial: RAW, STG, CORE, MART databases/schemas. Load the generated files through a stage and COPY INTO. Write ADR-002 on environment and account strategy. | J5: Scripts rerun from scratch; ADR-002 written | K5: D07, D08 | L5: 5 | M5: 5 | N5: Not started | Q5: Snowflake documentation: key concepts, architecture, virtual warehouses, loading | R5: https://docs.snowflake.com | S5: Hands-On Essentials: Data Warehousing workshop (free refresher on the basics) | T5: https://learn.snowflake.com/en/pages/hands-on-essentials-track
A6: 5 | B6: =Dashboard!$B$4+(A6-1)*7 -> 46342 | C6: 2 SnowPro Core | D6: Core domains: account access and security (RBAC, masking), structured and semi-structured data, transformations | E6: Snowflake docs: access control and column-level security | F6: https://docs.snowflake.com/en/user-guide/security-column-intro | G6: CORE: same course, account access, security and semi-structured data sections | H6: Implement the role hierarchy as SQL scripts. Mask PII (email, phone) and restrict rows by region. Test with at least 3 roles and save the test queries and results. | J6: Test queries show different roles see different data | K6: D09 | L6: 5 | M6: 5 | N6: Not started | Q6: Snowflake documentation: semi-structured data and transformations | R6: https://docs.snowflake.com | S6: Core exam page: re-read the objectives for security and data protection | T6: https://learn.snowflake.com/en/certifications/snowpro-core-c03
A7: 6 | B7: =Dashboard!$B$4+(A7-1)*7 -> 46349 | C7: 2 SnowPro Core | D7: Core domains: performance monitoring and optimization, Time Travel and cloning, data collaboration (sharing, Marketplace), connectivity. Practice exams, then take the Core exam | E7: Udemy: SnowPro Core COF-C03 practice exams x2 (pick one, see the Udemy Courses sheet) | G7: CORE: take 2 full practice exams early in the week (allow about 2 h each), log scores, review every wrong answer, then sit the Core exam on Friday | H7: Create a secure share for a fictional partner (a reduced mart, no PII). | I7: EXAM DAY (Friday): SnowPro Core | J7: Core exam passed; secure share works | K7: D10 | L7: 6 | M7: 4 | N7: Not started | Q7: Core exam page: check passing score, price and rules before booking | R7: https://learn.snowflake.com/en/certifications/snowpro-core-c03 | S7: Snowflake documentation: Time Travel, cloning, sharing, performance monitoring | T7: https://docs.snowflake.com
A8: 7 | B8: =Dashboard!$B$4+(A8-1)*7 -> 46356 | C8: 3 SnowPro Architect | D8: Architect domains: account and organization design, multi-account strategy, editions, regions | E8: Snowflake SnowPro Advanced Architect (ARA-C01) study guide | F8: https://learn.snowflake.com/courses/course-v1:snowflake+SPSG-ARA+A/about | G8: CORE: SnowPro Advanced Architect prep course, account/organization sections | H8: Build dbt bronze/silver/gold models with tests on Snowflake. | I8: BOOK the SnowPro Advanced: Architect exam for the Friday of week 12 (it needs an active SnowPro Core) | J8: dbt build passes on Snowflake | K8: D11 | L8: 4 | M8: 6 | N8: Not started | Q8: Snowflake documentation: organizations and accounts | R8: https://docs.snowflake.com | S8: Book: SnowPro Advanced Architect Certification Companion (R. Soni) | T8: https://www.oreilly.com/library/view/-/9781484292624/
A9: 8 | B9: =Dashboard!$B$4+(A9-1)*7 -> 46363 | C9: 3 SnowPro Architect | D9: Architect domains: security architecture at scale (RBAC design, network policies, tag-based masking, SSO/SCIM) | E9: Snowflake docs: column-level security and masking | F9: https://docs.snowflake.com/en/user-guide/security-column-intro | G9: CORE: same course, security and governance sections | H9: Extend the security setup: add a network policy and tag-based masking on classified columns, and write a short SSO/SCIM design (no real identity provider needed). | J9: Network policy and tag-based masking tested; SSO/SCIM note written | K9: D29 | L9: 4 | M9: 6 | N9: Not started | Q9: Snowflake documentation: RBAC and access control | R9: https://docs.snowflake.com | S9: Study guide: accounts and security domain | T9: https://learn.snowflake.com/courses/course-v1:snowflake+SPSG-ARA+A/about
A10: 9 | B10: =Dashboard!$B$4+(A10-1)*7 -> 46370 | C10: 3 SnowPro Architect | D10: Architect domains: data sharing, replication, failover, business continuity, listings, clean rooms | E10: Snowflake Quickstarts: data sharing and replication | F10: https://quickstarts.snowflake.com | G10: CORE: same course, sharing, replication and continuity sections | H10: Write the replication and failover design note for the platform (RPO/RTO, accounts, regions). | J10: Failover note committed | K10: D30 | L10: 4 | M10: 6 | N10: Not started | Q10: Hands-On Essentials: Collab, Marketplace and Cost Estimation (free, beginner level) | R10: https://learn.snowflake.com/en/pages/hands-on-essentials-track | S10: Snowflake documentation: replication and failover | T10: https://docs.snowflake.com
A11: 10 | B11: =Dashboard!$B$4+(A11-1)*7 -> 46377 | C11: 3 SnowPro Architect | D11: Architect domains: performance and cost (micro-partitions, clustering, search optimization, warehouse sizing, resource monitors) | E11: Snowflake documentation: performance and cost | F11: https://docs.snowflake.com | G11: CORE: same course, performance and cost sections | H11: Run clustering and warehouse-size experiments on larger data (e.g. the TPC-H sample) and write a short cost and performance report with query-profile screenshots. | J11: Report has real numbers | K11: D12 | L11: 4 | M11: 6 | N11: Not started | Q11: Snowflake sample data (TPC-H) for your experiments | R11: https://docs.snowflake.com/en/user-guide/sample-data | S11: AutomateDV worked example (optional second model) | T11: https://automate-dv.readthedocs.io/en/latest/worked_example/
A12: 11 | B12: =Dashboard!$B$4+(A12-1)*7 -> 46384 | C12: 3 SnowPro Architect | D12: Architect domains: Streams, Tasks, Dynamic Tables, Snowpipe, Iceberg | E12: Snowflake docs: Dynamic Tables | F12: https://docs.snowflake.com/en/user-guide/dynamic-tables-about | G12: CORE: same course, data engineering sections (Streams, Tasks, Dynamic Tables) | H12: Add an incremental pipeline with Streams + Tasks or Dynamic Tables. Document when you would choose each. Stretch goal: one Iceberg table. | J12: New data flows without a full reload | K12: D13 | L12: 4 | M12: 6 | N12: Not started | Q12: Hands-On Essentials: Data Engineering workshop (free, beginner level) | R12: https://learn.snowflake.com/en/pages/hands-on-essentials-track | S12: Apache Iceberg docs (stretch goal) | T12: https://iceberg.apache.org/docs/latest/
A13: 12 | B13: =Dashboard!$B$4+(A13-1)*7 -> 46391 | C13: 3 SnowPro Architect | D13: Review week: scenario questions and weak areas, then take the SnowPro Advanced: Architect exam | E13: Udemy: SnowPro Architect practice exams x2 (your pick) | G13: CORE: take 2 SnowPro Architect practice exams early in the week (allow about 2 h each), log scores, review every wrong answer, then sit the exam | H13: Draw architecture diagram v1 (Snowflake side). Reuse your ADRs as exam scenario practice. | I13: EXAM DAY (Friday): SnowPro Advanced: Architect | J13: Exam passed (check the vendor's passing score); diagram v1 committed | K13: D14 | L13: 6 | M13: 4 | N13: Not started | Q13: Study guide: domains and weights | R13: https://learn.snowflake.com/courses/course-v1:snowflake+SPSG-ARA+A/about | S13: Snowflake certification page (check passing score and rules) | T13: https://learn.snowflake.com
A14: 13 | B14: =Dashboard!$B$4+(A14-1)*7 -> 46398 | C14: 4 GCP Data Engineer | D14: Exam guide gap analysis, BigQuery design: partitioning, clustering, slots, authorized views | E14: Google Skills: Professional Data Engineer learning path (free 30 days for new users: start now, finish by week 13) | F14: https://www.skills.google/paths/16 | G14: CORE: Professional Data Engineer prep course, BigQuery and design sections | H14: Create the GCP project with a budget alert. Load a subset of the data to BigQuery via Cloud Storage. Design partitioning and clustering for the fact tables. START APPLYING to jobs from this week. | I14: BOOK the Professional Data Engineer exam for the Friday of week 17. START APPLYING to jobs | J14: Tables created; design explained; budget alert set; exam booked | K14: D15 | L14: 4 | M14: 6 | N14: Not started | Q14: Google guide: preparing for the Professional Data Engineer exam | R14: https://discuss.google.dev/t/your-guide-to-preparing-for-the-google-cloud-professional-data-engineer-certification/107505 | S14: Official exam guide (your checklist) | T14: https://cloud.google.com/learn/certification/data-engineer
A15: 14 | B15: =Dashboard!$B$4+(A15-1)*7 -> 46405 | C15: 4 GCP Data Engineer | D15: Pub/Sub, Dataflow (windows, triggers, watermarks), Dataproc | E15: Google Skills path: continue with the pipeline, Dataflow and Pub/Sub courses | F15: https://www.skills.google/paths/16 | G15: CORE: same course, Pub/Sub and Dataflow sections | H15: Build a small streaming slice: order events published to Pub/Sub and landed in BigQuery (BigQuery subscription or a small Dataflow template). Delete resources when done. | J15: Events arrive in BigQuery; resources deleted | K15: D16 | L15: 4 | M15: 6 | N15: Not started | Q15: Pub/Sub documentation | R15: https://cloud.google.com/pubsub/docs | S15: Dataflow documentation | T15: https://cloud.google.com/dataflow/docs
A16: 15 | B16: =Dashboard!$B$4+(A16-1)*7 -> 46412 | C16: 4 GCP Data Engineer | D16: Orchestration and storage choices: Composer, Bigtable, Spanner, GCS classes | E16: Google Skills path: continue with orchestration and storage courses | F16: https://www.skills.google/paths/16 | G16: CORE: same course, orchestration and storage sections. OPTIONAL: an Airflow course | H16: Run Airflow locally in Docker and write a DAG that triggers ingestion and dbt. Write a storage-choice matrix (latency, scale, consistency, cost). Composer is paid, so cover it on paper. | J16: DAG runs locally; storage-choice table written | K16: D17 | L16: 4 | M16: 6 | N16: Not started | Q16: Apache Airflow documentation | R16: https://airflow.apache.org/docs/ | S16: Book: Professional Data Engineer Study Guide (O'Reilly, recommended by Google)
A17: 16 | B17: =Dashboard!$B$4+(A17-1)*7 -> 46419 | C17: 4 GCP Data Engineer | D17: IAM, VPC Service Controls, CMEK, DLP, Dataplex | E17: Google Skills path: finish with security and governance courses | F17: https://www.skills.google/paths/16 | G17: CORE: same course, security and governance sections | H17: Apply least-privilege IAM to the project. Run a DLP inspection on the PII sample. Write a short GCP security and governance note. | J17: Security note committed | K17: D18 | L17: 4 | M17: 6 | N17: Not started | Q17: Dataplex documentation | R17: https://cloud.google.com/dataplex/docs | S17: Sensitive Data Protection (DLP) documentation | T17: https://cloud.google.com/sensitive-data-protection/docs
A18: 17 | B18: =Dashboard!$B$4+(A18-1)*7 -> 46426 | C18: 4 GCP Data Engineer | D18: Review week: practice questions, weak topics, then take the Professional Data Engineer exam | E18: Udemy: Professional Data Engineer practice exams x2 (your pick) | G18: CORE: take 2 Professional Data Engineer practice exams early in the week, log scores, review every wrong answer, then sit the exam | H18: Write ADR-004: Snowflake vs BigQuery for this platform, with a cost comparison for 3 workloads. | I18: EXAM DAY (Friday): Google Professional Data Engineer | J18: Exam passed; ADR-004 written | K18: D19 | L18: 6 | M18: 4 | N18: Not started | Q18: Official exam guide | R18: https://cloud.google.com/learn/certification/data-engineer | S18: BigQuery documentation (for ADR-004) | T18: https://cloud.google.com/bigquery/docs
A19: 18 | B19: =Dashboard!$B$4+(A19-1)*7 -> 46433 | C19: 5 Governance & CDMP | D19: Data governance, quality, metadata, lineage | E19: dbt docs: Data tests | F19: https://docs.getdbt.com/docs/build/data-tests | G19: OPTIONAL: data governance or data quality course | H19: Add dbt data-quality tests and freshness checks. Stand up lineage and a catalog locally (OpenMetadata or Marquez/OpenLineage in Docker) and capture lineage for one pipeline. | I19: BOOK the CDMP exam for the Friday of week 21 | J19: Quality tests added; lineage screenshot for one pipeline; exam booked | K19: D20 | L19: 4 | M19: 6 | N19: Not started | Q19: OpenMetadata documentation (local catalog and lineage) | R19: https://docs.open-metadata.org | S19: OpenLineage | T19: https://openlineage.io
A20: 19 | B20: =Dashboard!$B$4+(A20-1)*7 -> 46440 | C20: 5 Governance & CDMP | D20: MDM, reference data, integration and interoperability (map Talend/Lobster to DMBOK) | E20: DAMA: DMBOK knowledge areas | F20: https://www.dama.org | G20: CORE: the CDMP summary-notes course named in Resource 2 (check update date and reviews). OPTIONAL: master data management course | H20: Build a customer golden record: match/merge rules in SQL/Python, survivorship logic, and a reference-data table. Document the rules. | J20: Match/merge rules documented and tested | K20: D21 | L20: 4 | M20: 6 | N20: Not started | Q20: Udemy: Do-It-Yourself CDMP Exam Preparation, DMBOKv2 summary notes (check date and reviews) | R20: https://www.udemy.com/course/do-it-yourself-cdmp-exam-preparation-dmbokv2-summary-notes/ | S20: CDMP exam information | T20: https://cdmp.info
A21: 20 | B21: =Dashboard!$B$4+(A21-1)*7 -> 46447 | C21: 5 Governance & CDMP | D21: Data architecture, privacy, GDPR, data mesh vs data fabric | E21: Anthropic Academy: Introduction to Model Context Protocol (free) | F21: https://anthropic.skilljar.com/introduction-to-model-context-protocol/296690 | G21: OPTIONAL: GDPR for data professionals (the MCP courses are free, see Resources 1 and 2) | H21: Build the MCP server: expose 3 to 5 governed views, the data dictionary and lineage lookup to an AI agent, with role-based access. Test it with Claude Desktop. | J21: MCP server works with an AI agent and respects roles | K21: D22 | L21: 4 | M21: 6 | N21: Not started | Q21: DeepLearning.AI: MCP: Build Rich-Context AI Apps with Anthropic (about 1 h 40; check it is still free) | R21: https://learn.deeplearning.ai/courses/mcp-build-rich-context-ai-apps-with-anthropic/information | S21: MCP documentation | T21: https://modelcontextprotocol.io
A22: 21 | B22: =Dashboard!$B$4+(A22-1)*7 -> 46454 | C22: 5 Governance & CDMP | D22: CDMP Fundamentals practice questions, then take the exam | E22: Udemy: CDMP Data Management Exam Prep, 800 practice questions (check date and reviews) | F22: https://www.udemy.com/course/cdmp-data-management-exam-prep-800-practice-questions/ | G22: CORE: the 800 practice-questions course named in Resource 1; log every score on the Practice Exams sheet, then sit the exam | H22: Write the governance and GDPR design: data classification, retention, right-to-erasure approach, data ownership. | I22: EXAM DAY (Friday): CDMP Fundamentals | J22: Exam passed; governance and GDPR design written | K22: D23 | L22: 6 | M22: 4 | N22: Not started | Q22: The DMBOK book is the real source: borrow it or ask your employer | S22: CDMP exam information | T22: https://cdmp.info
A23: 22 | B23: =Dashboard!$B$4+(A23-1)*7 -> 46461 | C23: 6 Portfolio & Job Search | D23: Architecture communication: C4 model, diagrams for business vs technical audiences | E23: The C4 model | F23: https://c4model.com | G23: OPTIONAL: software architecture / C4 model course | H23: Polish the portfolio: final C4 diagrams, README, runbook, cost analysis, and a 5 to 10 minute demo video. | J23: A stranger can run the project from the README; demo video recorded | K23: D24, D25, D26 | L23: 0 | M23: 10 | N23: Not started | Q23: ADR templates | R23: https://adr.github.io
A24: 23 | B24: =Dashboard!$B$4+(A24-1)*7 -> 46468 | C24: 6 Portfolio & Job Search | D24: Interview preparation: system-design questions, trade-off storytelling | E24: ADR templates and your own ADRs (use them as interview stories) | F24: https://adr.github.io | G24: OPTIONAL: system design interview course | H24: Rewrite your CV for architect roles, publish a LinkedIn write-up, and run 3 mock architecture interviews (use your ADRs as stories). | J24: CV rewritten; LinkedIn post published; 3 mock interviews done | K24: D27, D28 | L24: 0 | M24: 10 | N24: Not started
A25: TOTAL | L25: =SUM(L2:L24) -> 94 | M25: =SUM(M2:M24) -> 136 | O25: =SUM(O2:O24) -> 0

Sheet Resources
A1: # | B1: Resource | C1: Type | D1: Cost (as found) | E1: Duration (as stated) | F1: Weeks | G1: Priority | H1: Link | I1: Status [EDIT] | J1: Notes
A2: 1 | B2: Dimensional Modeling and the Star Schema (Data Modeling for Analytics guide) | C2: Guide | D2: Free | F2: 1 | G2: CORE | H2: https://coginiti.co/learning/data-modeling/dimensional-modeling-star-schema/ | I2: Not started | J2: Explains grain, facts, dimensions and surrogate keys in order; has a next chapter on fact table design.
A3: 2 | B3: Understand star schema (Microsoft Learn) | C3: Article | D3: Free | F3: 1 | G3: CORE | H3: https://learn.microsoft.com/power-bi/guidance/star-schema | I3: Not started | J3: Power BI oriented and not a full treatment; use it as a second explanation.
A4: 3 | B4: The Data Warehouse Toolkit, Kimball and Ross, chapters 1-3 | C4: Book | D4: Paid (borrow) | F4: 1 | G4: OPTIONAL | I4: Not started | J4: Source of the Kimball techniques; open it only if a concept stays unclear after the build.
A5: 4 | B5: Kimball Dimensional Modeling Techniques | C5: Reference | D5: Free | F5: 1-3 | G5: REFERENCE | H5: https://www.kimballgroup.com/data-warehouse-business-intelligence-resources/kimball-techniques/dimensional-modeling-techniques/ | I5: Not started | J5: Summary only; use it as a checklist while you build.
A6: 5 | B6: dbt Fundamentals (dbt Labs) | C6: Course | D6: Free | E6: about 5 h (third-party listing) | F6: 2 | G6: CORE | H6: https://learn.getdbt.com | I6: Not started | J6: Official free starter course covering models, tests and documentation.
A7: 6 | B7: dbt docs: Snapshots | C7: Docs | D7: Free | F7: 2 | G7: CORE | H7: https://docs.getdbt.com/docs/build/snapshots | I7: Not started | J7: How SCD2 is done in dbt.
A8: 7 | B8: Data Vault 2.0: hubs, links, satellites (DEV Community) | C8: Article | D8: Free | F8: 3 | G8: CORE | H8: https://dev.to/gowthampotureddi/data-vault-2-0-for-data-engineering-hubs-links-satellites-hash-keys-automation-4bah | I8: Not started | J8: Concepts and trade-offs versus a star schema.
A9: 8 | B9: AutomateDV worked example (Data Vault on Snowflake TPC-H) | C9: Tutorial | D9: Free | F9: 3, 10 | G9: CORE | H9: https://automate-dv.readthedocs.io/en/latest/worked_example/ | I9: Not started | J9: Needs a Snowflake trial and the TPC-H sample data. Its page says using a corporate account is at your own risk, so use a personal trial.
A10: 9 | B10: SnowPro Core (COF-C03) official exam page | C10: Official page | D10: Free | F10: 4-6 | G10: CORE | H10: https://learn.snowflake.com/en/certifications/snowpro-core-c03 | I10: Not started | J10: Lists what the exam tests and recommends 6+ months of Snowflake experience. COF-C03 replaced COF-C02 on 16 Feb 2026; confirm exam code, price and rules here before booking.
A11: 10 | B11: Snowflake documentation (Core topics: architecture, warehouses, loading, security, sharing) | C11: Docs | D11: Free | F11: 4-6 | G11: CORE | H11: https://docs.snowflake.com | I11: Not started | J11: Main source for Core. Many third-party guides cover the retired COF-C02, so check them against the official page.
A12: 11 | B12: Snowflake Hands-On Essentials track | C12: Workshops | D12: Free | F12: 4, 9, 11 | G12: OPTIONAL | H12: https://learn.snowflake.com/en/pages/hands-on-essentials-track | I12: Not started | J12: Aimed at beginners, so useful as a quick Core refresher (Data Warehousing workshop, week 4). Later: the Collab/Marketplace/Cost Estimation workshop (week 9) and Data Engineering (week 11).
A13: 12 | B13: Udemy: Snowflake Core COF-C03 Certification Practice Tests | C13: Udemy practice tests | D13: Your Udemy access | E13: 2 tests of 100 questions | F13: 6 | G13: CORE | H13: https://www.udemy.com/course/snowflake-core-cof-c03-certification-practice-tests/ | I13: Not started | J13: Found by search; check update date and reviews.
A14: 13 | B14: Udemy: 5 Practice Exams for COF-C03 Snowflake Core Certification | C14: Udemy practice tests | D14: Your Udemy access | E14: 5 tests of 100 questions, 1 h 55 min each | F14: 6 | G14: OPTIONAL | H14: https://www.udemy.com/course/5-practice-exams-cof-c02-snowflake-core-certification | I14: Not started | J14: Found by search; check update date and reviews. The page address mentions COF-C02, so confirm the content is COF-C03.
A15: 14 | B15: Udemy: Practice Tests for the SnowPro Core Exam (COF-C02/C03) | C15: Udemy practice tests | D15: Your Udemy access | E15: 3 tests of 100 questions | F15: 6 | G15: OPTIONAL | H15: https://www.udemy.com/course/snowpro-core-certification-exam-practice-tests/ | I15: Not started | J15: Found by search; only the last test is described as covering COF-C03.
A16: 15 | B16: SnowPro Advanced: Architect (ARA-C01) study guide | C16: Official guide | D16: Free (check access) | F16: 7-12 | G16: CORE | H16: https://learn.snowflake.com/courses/course-v1:snowflake+SPSG-ARA+A/about | I16: Not started | J16: Lists domains, weights and doc links per topic. The page showed 'enrollment closed' when I checked, so also look for the current exam guide on Snowflake's certification page.
A17: 16 | B17: Snowflake documentation | C17: Docs | D17: Free | F17: 7-11 | G17: CORE | H17: https://docs.snowflake.com | I17: Not started | J17: Primary source for every exam topic.
A18: 17 | B18: Snowflake Quickstarts | C18: Hands-on guides | D18: Free | F18: 9 | G18: CORE | H18: https://quickstarts.snowflake.com | I18: Not started
A19: 18 | B19: SnowPro Advanced Architect Certification Companion (Ruchi Soni, Apress) | C19: Book | D19: Paid (check O'Reilly access) | F19: 7-11 | G19: OPTIONAL | H19: https://www.oreilly.com/library/view/-/9781484292624/ | I19: Not started | J19: Covers the four exam domains. Check whether your company has O'Reilly access.
A20: 19 | B20: Professional Data Engineer learning path (Google Skills) | C20: Course path | D20: Free 30 days for new users | E20: 13 activities | F20: 13-16 | G20: CORE | H20: https://www.skills.google/paths/16 | I20: Not started | J20: Start it in week 10 and finish by week 13 so the free period covers it.
A21: 20 | B21: Your guide to preparing for the Professional Data Engineer certification (Google) | C21: Guide | D21: Free | F21: 13 | G21: CORE | H21: https://discuss.google.dev/t/your-guide-to-preparing-for-the-google-cloud-professional-data-engineer-certification/107505 | I21: Not started | J21: Google's own preparation steps and tips.
A22: 21 | B22: Professional Data Engineer exam guide | C22: Official guide | D22: Free | F22: 13-17 | G22: CORE | H22: https://cloud.google.com/learn/certification/data-engineer | I22: Not started | J22: Use it as your checklist.
A23: 22 | B23: Pub/Sub, Dataflow and BigQuery documentation | C23: Docs | D23: Free | F23: 14, 17 | G23: CORE | H23: https://cloud.google.com/pubsub/docs | I23: Not started
A24: 23 | B24: Apache Airflow documentation | C24: Docs | D24: Free | F24: 15 | G24: CORE | H24: https://airflow.apache.org/docs/ | I24: Not started
A25: 24 | B25: Dataplex documentation | C25: Docs | D25: Free | F25: 16 | G25: CORE | H25: https://cloud.google.com/dataplex/docs | I25: Not started
A26: 25 | B26: Professional Data Engineer Study Guide (O'Reilly) | C26: Book | D26: Paid (check access) | F26: 13-17 | G26: OPTIONAL | I26: Not started | J26: Recommended in Google's preparation guide.
A27: 26 | B27: dbt docs: Data tests | C27: Docs | D27: Free | F27: 18 | G27: CORE | H27: https://docs.getdbt.com/docs/build/data-tests | I27: Not started
A28: 27 | B28: OpenMetadata documentation | C28: Docs | D28: Free | F28: 18 | G28: OPTIONAL | H28: https://docs.open-metadata.org | I28: Not started | J28: Local catalog and lineage in Docker. Alternative: OpenLineage.
A29: 28 | B29: OpenLineage | C29: Docs | D29: Free | F29: 18 | G29: OPTIONAL | H29: https://openlineage.io | I29: Not started
A30: 29 | B30: DAMA knowledge areas | C30: Reference | D30: Free | F30: 19 | G30: CORE | H30: https://www.dama.org | I30: Not started
A31: 30 | B31: CDMP exam information | C31: Official page | D31: Free | F31: 18-21 | G31: CORE | H31: https://cdmp.info | I31: Not started | J31: The DMBOK book is the real source for the exam; borrow it or ask your employer.
A32: 31 | B32: Udemy: Do-It-Yourself CDMP Exam Preparation: DMBOKv2 Summary Notes | C32: Udemy course | D32: Your Udemy access | F32: 19-21 | G32: OPTIONAL | H32: https://www.udemy.com/course/do-it-yourself-cdmp-exam-preparation-dmbokv2-summary-notes/ | I32: Not started | J32: Summary notes, not the DMBOK itself. Check update date and reviews.
A33: 32 | B33: Udemy: CDMP Data Management Exam Prep: 800 Practice Questions | C33: Udemy practice tests | D33: Your Udemy access | E33: 6 practice tests | F33: 21 | G33: CORE | H33: https://www.udemy.com/course/cdmp-data-management-exam-prep-800-practice-questions/ | I33: Not started | J33: Check update date and reviews before relying on it.
A34: 33 | B34: Introduction to Model Context Protocol (Anthropic Academy) | C34: Course | D34: Free | F34: 20 | G34: CORE | H34: https://anthropic.skilljar.com/introduction-to-model-context-protocol/296690 | I34: Not started | J34: Builds MCP servers and clients with the Python SDK and includes the MCP Inspector.
A35: 34 | B35: MCP: Build Rich-Context AI Apps with Anthropic (DeepLearning.AI) | C35: Short course | D35: Free (check current access) | E35: about 1 h 40 | F35: 20 | G35: CORE | H35: https://learn.deeplearning.ai/courses/mcp-build-rich-context-ai-apps-with-anthropic/information | I35: Not started | J35: Build and deploy an MCP server. The page said access was free for a limited time during a beta, so check.
A36: 35 | B36: Model Context Protocol documentation | C36: Docs | D36: Free | F36: 20 | G36: CORE | H36: https://modelcontextprotocol.io | I36: Not started
A37: 36 | B37: CNIL (French data protection authority) | C37: Guidance | D37: Free | F37: 20-21 | G37: OPTIONAL | H37: https://www.cnil.fr | I37: Not started | J37: GDPR guidance, in French.
A38: 37 | B38: The C4 model | C38: Reference | D38: Free | F38: 22 | G38: CORE | H38: https://c4model.com | I38: Not started
A39: 38 | B39: Architecture Decision Records (ADR templates) | C39: Reference | D39: Free | F39: 3, 22-23 | G39: CORE | H39: https://adr.github.io | I39: Not started
A41: Links were checked by web search on 17 Oct 2026. Free or paid status is as found; confirm before relying on it. Courses I only know from their descriptions are marked 'check date and reviews'.

Sheet Project Overview
A1: Item | B1: Description
A2: Project name | B2: OrderFlow: an end-to-end Order-to-Cash data platform (one project used in every phase)
A3: Business scenario | B3: A mid-size B2B distributor receives purchase orders, shipping notices and invoices from partners via EDI/API files. Finance, sales and logistics need trusted, secure, governed data, and AI agents need governed access to it.
A4: Data sources | B4: (1) Synthetic EDI/API-style data from your Python generator (850 purchase order, 856 shipping notice, 810 invoice, payments, customers, products), with injected duplicates, late events and bad records. (2) Snowflake sample data (TPC-H) for volume and performance tests. No employer data.
A5: Architecture layers | B5: Ingestion (files/API/events) > RAW > STG > CORE (Kimball, with Data Vault option documented) > MART > serving (BI, data share, MCP server)
A6: Platforms | B6: Snowflake (primary), BigQuery (secondary, for comparison and the GCP exam), dbt for transformation, Airflow (local Docker) for orchestration, OpenMetadata or Marquez/OpenLineage for catalog and lineage
A7: Where your experience shows | B7: Ingestion design and file/EDI handling come from your Talend/Lobster background. Say so in the README and map the patterns you used.
A8: Cost guardrails | B8: Use Snowflake trial credits and a small warehouse with auto-suspend and a resource monitor. In GCP set a budget alert on day 1, avoid always-on services (Composer, Dataflow jobs) and delete resources after each exercise. Check vendor pricing pages before turning anything on.
A9: Repo structure | B9: docs/ (architecture, requirements) | adr/ (decision records) | ingestion/ (generator, loaders) | dbt/ | infra/ (SQL/Terraform scripts for roles, policies) | orchestration/ | mcp/ | governance/
A10: Definition of done | B10: A stranger can read the README, understand the architecture in 5 minutes, run the pipeline from scratch, and see 4 ADRs showing trade-offs and costs. A 5 to 10 minute demo video walks through it.
A11: Scope rule | B11: One finished, documented project beats four half-built ones. Cut stretch goals (Iceberg, Dataflow, Composer) before cutting documentation.

Sheet Udemy Courses
A1: Slot | B1: Priority | C1: Weeks | D1: Search keywords on Udemy | E1: Course title (you fill) [EDIT] | F1: Last updated (you fill) [EDIT] | G1: Updated in last 12 months? | H1: Rating (you fill) [EDIT] | I1: Video hours (you fill) [EDIT] | J1: Status [EDIT] | K1: Candidates I found (verify before use)
A2: SnowPro Core prep (COF-C03) | B2: CORE | C2: 4-6 | D2: SnowPro Core COF-C03 | G2: =IF(F2="","",IF(TODAY()-F2<=365,"Yes","No: check another course")) | J2: Not started | K2: Prep courses: check the course says COF-C03 (older ones cover the retired COF-C02). Search 'SnowPro Core COF-C03'
A3: SnowPro Core practice exams | B3: CORE | C3: 6 | D3: SnowPro Core COF-C03 practice exam | G3: =IF(F3="","",IF(TODAY()-F3<=365,"Yes","No: check another course")) | J3: Not started | K3: Snowflake Core COF-C03 Certification Practice Tests (200 questions); 5 Practice Exams for COF-C03 (500 questions); Practice Tests for the SnowPro Core Exam COF-C02/C03 (found by search; check update date and reviews)
A4: SnowPro Advanced Architect prep | B4: CORE | C4: 7-12 | D4: SnowPro Advanced Architect ARA-C01 | G4: =IF(F4="","",IF(TODAY()-F4<=365,"Yes","No: check another course")) | J4: Not started | K4: None verified: search with the keywords and apply the checks below
A5: SnowPro Architect practice exams | B5: CORE | C5: 12 | D5: SnowPro Advanced Architect practice exam | G5: =IF(F5="","",IF(TODAY()-F5<=365,"Yes","No: check another course")) | J5: Not started | K5: None verified: search with the keywords and apply the checks below
A6: GCP Professional Data Engineer prep | B6: CORE | C6: 13-17 | D6: Google Professional Data Engineer certification | G6: =IF(F6="","",IF(TODAY()-F6<=365,"Yes","No: check another course")) | J6: Not started | K6: None verified: search with the keywords and apply the checks below
A7: GCP Professional Data Engineer practice exams | B7: CORE | C7: 17 | D7: Professional Data Engineer practice exam | G7: =IF(F7="","",IF(TODAY()-F7<=365,"Yes","No: check another course")) | J7: Not started | K7: None verified: search with the keywords and apply the checks below
A8: CDMP / DAMA-DMBOK prep or practice | B8: CORE | C8: 19-21 | D8: CDMP DAMA DMBOK | G8: =IF(F8="","",IF(TODAY()-F8<=365,"Yes","No: check another course")) | J8: Not started | K8: CDMP Data Management Exam Prep: 800 Practice Questions; Do-It-Yourself CDMP Exam Preparation: DMBOKv2 Summary Notes (found by search; check update date and reviews)
A9: Data modeling / Data Vault | B9: OPTIONAL | C9: 1-3 | D9: data modeling Kimball; Data Vault 2.0 | G9: =IF(F9="","",IF(TODAY()-F9<=365,"Yes","No: check another course")) | J9: Not started | K9: None verified: search with the keywords and apply the checks below
A10: Airflow | B10: OPTIONAL | C10: 15 | D10: Apache Airflow | G10: =IF(F10="","",IF(TODAY()-F10<=365,"Yes","No: check another course")) | J10: Not started | K10: None verified: search with the keywords and apply the checks below
A11: Data governance, MDM and GDPR | B11: OPTIONAL | C11: 18-20 | D11: data governance; master data management; GDPR | G11: =IF(F11="","",IF(TODAY()-F11<=365,"Yes","No: check another course")) | J11: Not started | K11: None verified: search with the keywords and apply the checks below
A12: MCP / AI agents | B12: OPTIONAL | C12: 20 | D12: Model Context Protocol; AI agents | G12: =IF(F12="","",IF(TODAY()-F12<=365,"Yes","No: check another course")) | J12: Not started | K12: Free alternatives, no Udemy needed: Anthropic Academy 'Introduction to Model Context Protocol'; DeepLearning.AI 'MCP: Build Rich-Context AI Apps with Anthropic'
A13: Architecture and system design interviews | B13: OPTIONAL | C13: 22-23 | D13: software architecture; system design interview | G13: =IF(F13="","",IF(TODAY()-F13<=365,"Yes","No: check another course")) | J13: Not started | K13: None verified: search with the keywords and apply the checks below
A15: How to choose: (1) exact exam name, not the associate level, (2) updated within 12 months, (3) recent reviews from people who passed, (4) one course per exam. Do not buy or enrol in several courses for the same exam.
A16: Course titles are not listed here because availability and quality change; search with the keywords and fill in your pick. Check whether Udemy Business includes learning paths or labs.

Sheet Practice Exams
A1: Exam [EDIT] | B1: Attempt # [EDIT] | C1: Date [EDIT] | D1: Score (%) [EDIT] | E1: Weak areas found [EDIT] | F1: Next action [EDIT] | H1: Legend
A2: EXAMPLE SnowPro Advanced: Architect | B2: 1 | C2: 46374 | D2: 0.68 | E2: Replication and failover, cost controls | F2: Redo the week 6 and 7 experiments (example row, ignored by the Dashboard) | H2: Enter scores as percentages (e.g. 72%). Pick the exam from the dropdown starting at row 3 so the Dashboard counts it.
H3: Row 2 is an example and is not counted.

Sheet Deliverables
A1: ID | B1: Week | C1: Due (suggested) | D1: Type | E1: Deliverable | F1: Proof of done | G1: Status [EDIT] | H1: GitHub link (you fill) [EDIT]
A2: D01 | B2: 1 | C2: =Dashboard!$B$4+B2*7-3 -> 46318 | D2: Doc | E2: Requirements, scenario and data-source inventory | F2: README section committed to the repo | G2: Not started
A3: D02 | B3: 1 | C3: =Dashboard!$B$4+B3*7-3 -> 46318 | D3: Model | E3: Bus matrix for order-to-cash | F3: Matrix in docs/ listing processes and conformed dimensions | G3: Not started
A4: D03 | B4: 2 | C4: =Dashboard!$B$4+B4*7-3 -> 46325 | D4: Code | E4: Python synthetic data generator (EDI/API-style) | F4: Script runs and produces files with injected defects | G4: Not started
A5: D04 | B5: 2 | C5: =Dashboard!$B$4+B5*7-3 -> 46325 | D5: Code | E5: dbt project initialized with SCD2 customer snapshot | F5: dbt snapshot runs; history rows visible | G5: Not started
A6: D05 | B6: 3 | C6: =Dashboard!$B$4+B6*7-3 -> 46332 | D6: Diagram | E6: Order-to-cash logical model | F6: dbdiagram export committed | G6: Not started
A7: D06 | B7: 3 | C7: =Dashboard!$B$4+B7*7-3 -> 46332 | D7: ADR | E7: ADR-001: Kimball vs Data Vault per layer | F7: Decision, options, trade-offs, consequences | G7: Not started
A8: D07 | B8: 4 | C8: =Dashboard!$B$4+B8*7-3 -> 46339 | D8: Code | E8: Snowflake environment scripts and raw load | F8: Scripts rerunnable from scratch | G8: Not started
A9: D08 | B9: 4 | C9: =Dashboard!$B$4+B9*7-3 -> 46339 | D9: ADR | E9: ADR-002: account and environment strategy | F9: Single vs multi-account, naming, regions | G9: Not started
A10: D09 | B10: 5 | C10: =Dashboard!$B$4+B10*7-3 -> 46346 | D10: Code | E10: RBAC, masking and row access scripts with test queries | F10: Test results showing different roles see different data | G10: Not started
A11: D10 | B11: 6 | C11: =Dashboard!$B$4+B11*7-3 -> 46353 | D11: Doc | E11: Secure share for a fictional partner (reduced mart, no PII) | F11: Share works from a second account or a reader account | G11: Not started
A12: D11 | B12: 7 | C12: =Dashboard!$B$4+B12*7-3 -> 46360 | D12: Code | E12: dbt bronze/silver/gold models with tests | F12: dbt build passes | G12: Not started
A13: D12 | B13: 10 | C13: =Dashboard!$B$4+B13*7-3 -> 46381 | D13: Doc | E13: Performance and cost report | F13: Experiments with numbers and query profile screenshots | G13: Not started
... A31: D30 | B31: 9 | C31: =Dashboard!$B$4+B31*7-3 -> 46374 | D31: Doc | E31: Replication and failover design note (RPO/RTO) | F31: Note committed with accounts, regions and recovery targets | G31: Not started

Sheet Certifications
A1: Certification | B1: Target exam week | C1: Exam date (suggested, overwrite) | D1: Cost (you fill, check vendor page) [EDIT] | E1: Status [EDIT] | F1: Official page | G1: Book exam by (suggested)
A2: SnowPro Advanced: Architect | B2: 12 | C2: =Dashboard!$B$4+B2*7-3 -> 46395 | E2: Not started | F2: https://learn.snowflake.com | G2: =Dashboard!$B$4+(7-1)*7 -> 46356
A3: Google Professional Data Engineer | B3: 17 | C3: =Dashboard!$B$4+B3*7-3 -> 46430 | E3: Not started | F3: https://cloud.google.com/learn/certification/data-engineer | G3: =Dashboard!$B$4+(13-1)*7 -> 46398
A4: CDMP Data Management Fundamentals | B4: 21 | C4: =Dashboard!$B$4+B4*7-3 -> 46458 | E4: Not started | F4: https://cdmp.info | G4: =Dashboard!$B$4+(18-1)*7 -> 46433
A5: SnowPro Core (COF-C03, prerequisite for the Architect exam) | B5: 6 | C5: =Dashboard!$B$4+B5*7-3 -> 46353 | E5: Not started | F5: https://learn.snowflake.com | G5: =Dashboard!$B$4+(3-1)*7 -> 46328
A6: Suggested date = Friday of the target week. Confirm exam codes, prices and domains on the vendor page before booking.

Sheet Application Log
A1: Company [EDIT] | B1: Role title [EDIT] | C1: Date applied [EDIT] | D1: Source [EDIT] | E1: Status [EDIT] | F1: Next step / notes [EDIT] | H1: Titles to search
A2: EXAMPLE Acme Corp | B2: Data Platform Architect | C2: 46370 | D2: LinkedIn | E2: Example | F2: Phone screen booked (example row, overwrite or delete) | H2: Data Architect
H3: Data Platform Architect
H4: Solutions Architect (data)
H5: Integration Architect
H6: Lead / Senior Data Engineer (architecture scope)
H7: Analytics Engineering Lead
H9: Start applying from week 13 (after SnowPro Architect). Use the project as your main proof.
